animalai/__init__.py
animalai/actions.py
animalai/environment.py
animalai/executable.py
animalai/play.py
animalai/raycastparser.py
animalai/agents/__init__.py
animalai/agents/braitenberg.py
animalai/agents/randomActionAgent.py
animalai/arenas/GoodGoal_Fixed.yml
animalai/arenas/GoodGoal_Random.yml
animalai/arenas/__init__.py
animalai-5.0.1.dist-info/METADATA
animalai-5.0.1.dist-info/WHEEL
animalai-5.0.1.dist-info/licenses/LICENSE
animalai-5.0.1.dist-info/RECORD
