Metadata-Version: 2.4
Name: animalai
Version: 5.0.1
Summary: Animal-AI Python API
Project-URL: Website, https://animalai.org/
Project-URL: Repository, https://github.com/Kinds-of-Intelligence-CFI/animal-ai-python
Project-URL: Main Repository, https://github.com/Kinds-of-Intelligence-CFI/animal-ai
Project-URL: Releases, https://https://github.com/Kinds-of-Intelligence-CFI/animal-ai/releases
Project-URL: Documentation, https://github.com/Kinds-of-Intelligence-CFI/animal-ai/tree/main/docs
Author: Matt Crosby, Ibrahim Alhas, Konstantinos Voudouris, Wout Schellaert, Joel Holmes, Ben Beyret, Ben Slater
Author-email: Animal-AI Team <kindsofintelligence.cfi@gmail.com>
License-Expression: MIT
License-File: LICENSE
Classifier: Intended Audience :: Developers
Classifier: Intended Audience :: Science/Research
Classifier: License :: OSI Approved :: Apache Software License
Classifier: Operating System :: MacOS :: MacOS X
Classifier: Operating System :: Microsoft :: Windows :: Windows 10
Classifier: Operating System :: Microsoft :: Windows :: Windows 11
Classifier: Operating System :: POSIX :: Linux
Classifier: Programming Language :: Python :: 3.10
Classifier: Topic :: Scientific/Engineering :: Artificial Intelligence
Requires-Python: <3.10.13,>=3.10.12
Requires-Dist: mlagents-envs>=1.0.0
Requires-Dist: numpy
Requires-Dist: protobuf==3.20.3
